Workbook

Sheet Executive Dashboard
A1: POS AGENT REVENUE & OPERATIONAL INSIGHTS DASHBOARD
A2: 3MTT Capstone Project | Agent Location: Yaba, Lagos | Period: March 2026 | Prepared for POS Business Growth
A4: TOTAL TRANSACTION VOLUME | C4: TOTAL NET PROFIT | E4: TOTAL TRANSACTIONS | G4: SUCCESS RATE | I4: AVG PROFIT / TX
A5: ='KPI Calculations'!B9 | C5: ='KPI Calculations'!E9 | E5: ='KPI Calculations'!C9 | G5: ='KPI Calculations'!D9/'KPI Calculations'!C9 | I5: ='KPI Calculations'!F9
A8: Key Performance Summaries
A9: Transaction Type | B9: Volume (NGN) | C9: Net Profit (NGN) | D9: Avg Profit/Tx | F9: Bank Name | G9: Total Txns | H9: Failed Txns | I9: Success Rate
A10: ='KPI Calculations'!A5 | B10: ='KPI Calculations'!B5 | C10: ='KPI Calculations'!E5 | D10: ='KPI Calculations'!F5 | F10: ='KPI Calculations'!A14 | G10: ='KPI Calculations'!B14 | H10: ='KPI Calculations'!D14 | I10: ='KPI Calculations'!E14
A11: ='KPI Calculations'!A6 | B11: ='KPI Calculations'!B6 | C11: ='KPI Calculations'!E6 | D11: ='KPI Calculations'!F6 | F11: ='KPI Calculations'!A15 | G11: ='KPI Calculations'!B15 | H11: ='KPI Calculations'!D15 | I11: ='KPI Calculations'!E15
A12: ='KPI Calculations'!A7 | B12: ='KPI Calculations'!B7 | C12: ='KPI Calculations'!E7 | D12: ='KPI Calculations'!F7 | F12: ='KPI Calculations'!A16 | G12: ='KPI Calculations'!B16 | H12: ='KPI Calculations'!D16 | I12: ='KPI Calculations'!E16
A13: ='KPI Calculations'!A8 | B13: ='KPI Calculations'!B8 | C13: ='KPI Calculations'!E8 | D13: ='KPI Calculations'!F8 | F13: ='KPI Calculations'!A17 | G13: ='KPI Calculations'!B17 | H13: ='KPI Calculations'!D17 | I13: ='KPI Calculations'!E17
A14: Total / Avg | B14: ='KPI Calculations'!B9 | C14: ='KPI Calculations'!E9 | D14: ='KPI Calculations'!F9 | F14: ='KPI Calculations'!A18 | G14: ='KPI Calculations'!B18 | H14: ='KPI Calculations'!D18 | I14: ='KPI Calculations'!E18
F15: ='KPI Calculations'!A19 | G15: ='KPI Calculations'!B19 | H15: ='KPI Calculations'!D19 | I15: ='KPI Calculations'!E19
F16: ='KPI Calculations'!A20 | G16: ='KPI Calculations'!B20 | H16: ='KPI Calculations'!D20 | I16: ='KPI Calculations'!E20
F17: ='KPI Calculations'!A21 | G17: ='KPI Calculations'!B21 | H17: ='KPI Calculations'!D21 | I17: ='KPI Calculations'!E21
A32: KEY STRATEGIC INSIGHTS FOR POS AGENT PROFITABILITY: 1. Top Profit Driver: Cash-Out (Withdrawals) contributes ~65% of net profit. Maintain sufficient cash float especially during weekend peaks. 2. Peak Demand Window: Transaction volumes spike between 4:00 PM and 7:00 PM. Agent should secure extra cash float before 3:30 PM. 3. Bank Network Downtime: Certain banks experience failure rates above 12%. Recommend routing transactions to alternative agent platforms during peak downtime hours. 4. Low-Margin Services: Airtime sales yield low absolute margin per transaction. Use airtime top-ups primarily as a foot-traffic driver for higher-margin Cash-Out services.

Sheet Pricing & Assumptions
A1: POS Agent Pricing Model & Fee Assumptions
A2: 3MTT Capstone Project | POS Agent Revenue Insights (Nigeria Context)
A4: Transaction Type | B4: Amount Tier (NGN) | C4: Customer Fee Charged (NGN) | D4: Provider Commission (NGN) | E4: Net Margin / Trade Note
A5: Cash-Out (Withdrawal) | B5: ₦1,000 - ₦5,000 | C5: 100 | D5: 25 | E5: Standard neighborhood rate
A6: Cash-Out (Withdrawal) | B6: ₦5,001 - ₦10,000 | C6: 200 | D6: 50 | E6: Capped provider charge
A7: Cash-Out (Withdrawal) | B7: ₦10,001 - ₦20,000 | C7: 300 | D7: 80 | E7: High volume cash-out
A8: Cash-In (Deposit) | B8: ₦1,000 - ₦10,000 | C8: 100 | D8: 30 | E8: Fixed deposit fee
A9: Cash-In (Deposit) | B9: ₦10,001 - ₦50,000 | C9: 200 | D9: 50 | E9: Agent transfer service
A10: Bill Payment (Utility/TV) | B10: Flat Fee | C10: 150 | D10: 50 | E10: DSTV / PHCN bill payments
A11: Airtime / Data Top-up | B11: Variable | C11: 2.0% Commission | D11: 0.5% Cost | E11: Agent retains 1.5% net margin
A14: Supported Banks / Networks
A15: GTBank
A16: Access Bank
A17: Zenith Bank
A18: First Bank
A19: Kuda Bank
A20: OPay
A21: Moniepoint
A22: UBA

Sheet Cleaned Transactions
A1: Transaction ID | B1: Timestamp | C1: Date | D1: Day of Week | E1: Hour | F1: Transaction Type | G1: Customer Bank | H1: Amount (NGN) | I1: Customer Fee (NGN) | J1: Provider Fee (NGN) | K1: Net Profit (NGN) | L1: Status | M1: Failure Reason
A2: POS-2026-0001 | B2: 2026-03-01 07:17:15 | C2: 2026-03-01 | D2: Sunday | E2: 7 | F2: Cash-Out | G2: Access Bank | H2: 3000 | I2: 100 | J2: 25 | K2: =I2-J2 | L2: Successful | M2: None
A3: POS-2026-0002 | B3: 2026-03-01 07:05:13 | C3: 2026-03-01 | D3: Sunday | E3: 7 | F3: Cash-Out | G3: GTBank | H3: 7000 | I3: 200 | J3: 50 | K3: =I3-J3 | L3: Successful | M3: None
A4: POS-2026-0003 | B4: 2026-03-01 15:26:14 | C4: 2026-03-01 | D4: Sunday | E4: 15 | F4: Cash-Out | G4: Kuda Bank | H4: 2000 | I4: 100 | J4: 25 | K4: =I4-J4 | L4: Successful | M4: None
A5: POS-2026-0004 | B5: 2026-03-01 10:27:21 | C5: 2026-03-01 | D5: Sunday | E5: 10 | F5: Cash-Out | G5: First Bank | H5: 15000 | I5: 300 | J5: 80 | K5: =I5-J5 | L5: Successful | M5: None
A6: POS-2026-0005 | B6: 2026-03-01 13:22:54 | C6: 2026-03-01 | D6: Sunday | E6: 13 | F6: Cash-Out | G6: Kuda Bank | H6: 2000 | I6: 100 | J6: 25 | K6: =I6-J6 | L6: Successful | M6: None
A7: POS-2026-0006 | B7: 2026-03-01 14:59:24 | C7: 2026-03-01 | D7: Sunday | E7: 14 | F7: Cash-Out | G7: Kuda Bank | H7: 15000 | I7: 300 | J7: 80 | K7: =I7-J7 | L7: Successful | M7: None
A8: POS-2026-0007 | B8: 2026-03-01 15:02:42 | C8: 2026-03-01 | D8: Sunday | E8: 15 | F8: Cash-Out | G8: Kuda Bank | H8: 3000 | I8: 100 | J8: 25 | K8: =I8-J8 | L8: Successful | M8: None
A9: POS-2026-0008 | B9: 2026-03-02 13:29:40 | C9: 2026-03-02 | D9: Monday | E9: 13 | F9: Bill Payment | G9: Zenith Bank | H9: 6000 | I9: 150 | J9: 50 | K9: =I9-J9 | L9: Successful | M9: None
A10: POS-2026-0009 | B10: 2026-03-02 15:44:59 | C10: 2026-03-02 | D10: Monday | E10: 15 | F10: Cash-In | G10: Access Bank | H10: 20000 | I10: 200 | J10: 50 | K10: =I10-J10 | L10: Successful | M10: None
A11: POS-2026-0010 | B11: 2026-03-02 14:15:10 | C11: 2026-03-02 | D11: Monday | E11: 14 | F11: Cash-Out | G11: Kuda Bank | H11: 7000 | I11: 200 | J11: 50 | K11: =I11-J11 | L11: Successful | M11: None
A12: POS-2026-0011 | B12: 2026-03-02 17:49:03 | C12: 2026-03-02 | D12: Monday | E12: 17 | F12: Cash-Out | G12: GTBank | H12: 15000 | I12: 300 | J12: 80 | K12: =I12-J12 | L12: Successful | M12: None
A13: POS-2026-0012 | B13: 2026-03-02 08:58:36 | C13: 2026-03-02 | D13: Monday | E13: 8 | F13: Bill Payment | G13: OPay | H13: 4500 | I13: 150 | J13: 50 | K13: =I13-J13 | L13: Successful | M13: None
... A269: POS-2026-0268 | B269: 2026-03-31 08:24:55 | C269: 2026-03-31 | D269: Tuesday | E269: 8 | F269: Cash-In | G269: First Bank | H269: 50000 | I269: 200 | J269: 50 | K269: =I269-J269 | L269: Successful | M269: None

Sheet KPI Calculations
A1: Aggregated KPI Engine & Pivot Summaries
A3: 1. Performance Breakdown by Transaction Type
A4: Transaction Type | B4: Total Volume (NGN) | C4: Total Count | D4: Successful Count | E4: Net Profit (NGN) | F4: Avg Profit / Tx (NGN)
A5: Cash-Out | B5: =SUMIFS('Cleaned Transactions'!H$2:H$269, 'Cleaned Transactions'!F$2:F$269, A5, 'Cleaned Transactions'!L$2:L$269, "Successful") | C5: =COUNTIF('Cleaned Transactions'!F$2:F$269, A5) | D5: =COUNTIFS('Cleaned Transactions'!F$2:F$269, A5, 'Cleaned Transactions'!L$2:L$269, "Successful") | E5: =SUMIF('Cleaned Transactions'!F$2:F$269, A5, 'Cleaned Transactions'!K$2:K$269) | F5: =IFERROR(E5/D5, 0)
A6: Cash-In | B6: =SUMIFS('Cleaned Transactions'!H$2:H$269, 'Cleaned Transactions'!F$2:F$269, A6, 'Cleaned Transactions'!L$2:L$269, "Successful") | C6: =COUNTIF('Cleaned Transactions'!F$2:F$269, A6) | D6: =COUNTIFS('Cleaned Transactions'!F$2:F$269, A6, 'Cleaned Transactions'!L$2:L$269, "Successful") | E6: =SUMIF('Cleaned Transactions'!F$2:F$269, A6, 'Cleaned Transactions'!K$2:K$269) | F6: =IFERROR(E6/D6, 0)
A7: Bill Payment | B7: =SUMIFS('Cleaned Transactions'!H$2:H$269, 'Cleaned Transactions'!F$2:F$269, A7, 'Cleaned Transactions'!L$2:L$269, "Successful") | C7: =COUNTIF('Cleaned Transactions'!F$2:F$269, A7) | D7: =COUNTIFS('Cleaned Transactions'!F$2:F$269, A7, 'Cleaned Transactions'!L$2:L$269, "Successful") | E7: =SUMIF('Cleaned Transactions'!F$2:F$269, A7, 'Cleaned Transactions'!K$2:K$269) | F7: =IFERROR(E7/D7, 0)
A8: Airtime | B8: =SUMIFS('Cleaned Transactions'!H$2:H$269, 'Cleaned Transactions'!F$2:F$269, A8, 'Cleaned Transactions'!L$2:L$269, "Successful") | C8: =COUNTIF('Cleaned Transactions'!F$2:F$269, A8) | D8: =COUNTIFS('Cleaned Transactions'!F$2:F$269, A8, 'Cleaned Transactions'!L$2:L$269, "Successful") | E8: =SUMIF('Cleaned Transactions'!F$2:F$269, A8, 'Cleaned Transactions'!K$2:K$269) | F8: =IFERROR(E8/D8, 0)
A9: Total | B9: =SUM(B5:B8) | C9: =SUM(C5:C8) | D9: =SUM(D5:D8) | E9: =SUM(E5:E8) | F9: =IFERROR(E9/D9, 0)
A12: 2. Network Reliability & Downtime by Bank
A13: Bank Name | B13: Total Txns | C13: Successful | D13: Failed | E13: Success Rate (%)
A14: GTBank | B14: =COUNTIF('Cleaned Transactions'!G$2:G$269, A14) | C14: =COUNTIFS('Cleaned Transactions'!G$2:G$269, A14, 'Cleaned Transactions'!L$2:L$269, "Successful") | D14: =COUNTIFS('Cleaned Transactions'!G$2:G$269, A14, 'Cleaned Transactions'!L$2:L$269, "Failed") | E14: =IFERROR(C14/B14, 0)
A15: Access Bank | B15: =COUNTIF('Cleaned Transactions'!G$2:G$269, A15) | C15: =COUNTIFS('Cleaned Transactions'!G$2:G$269, A15, 'Cleaned Transactions'!L$2:L$269, "Successful") | D15: =COUNTIFS('Cleaned Transactions'!G$2:G$269, A15, 'Cleaned Transactions'!L$2:L$269, "Failed") | E15: =IFERROR(C15/B15, 0)
A16: Zenith Bank | B16: =COUNTIF('Cleaned Transactions'!G$2:G$269, A16) | C16: =COUNTIFS('Cleaned Transactions'!G$2:G$269, A16, 'Cleaned Transactions'!L$2:L$269, "Successful") | D16: =COUNTIFS('Cleaned Transactions'!G$2:G$269, A16, 'Cleaned Transactions'!L$2:L$269, "Failed") | E16: =IFERROR(C16/B16, 0)
A17: First Bank | B17: =COUNTIF('Cleaned Transactions'!G$2:G$269, A17) | C17: =COUNTIFS('Cleaned Transactions'!G$2:G$269, A17, 'Cleaned Transactions'!L$2:L$269, "Successful") | D17: =COUNTIFS('Cleaned Transactions'!G$2:G$269, A17, 'Cleaned Transactions'!L$2:L$269, "Failed") | E17: =IFERROR(C17/B17, 0)
A18: Kuda Bank | B18: =COUNTIF('Cleaned Transactions'!G$2:G$269, A18) | C18: =COUNTIFS('Cleaned Transactions'!G$2:G$269, A18, 'Cleaned Transactions'!L$2:L$269, "Successful") | D18: =COUNTIFS('Cleaned Transactions'!G$2:G$269, A18, 'Cleaned Transactions'!L$2:L$269, "Failed") | E18: =IFERROR(C18/B18, 0)
A19: OPay | B19: =COUNTIF('Cleaned Transactions'!G$2:G$269, A19) | C19: =COUNTIFS('Cleaned Transactions'!G$2:G$269, A19, 'Cleaned Transactions'!L$2:L$269, "Successful") | D19: =COUNTIFS('Cleaned Transactions'!G$2:G$269, A19, 'Cleaned Transactions'!L$2:L$269, "Failed") | E19: =IFERROR(C19/B19, 0)
A20: Moniepoint | B20: =COUNTIF('Cleaned Transactions'!G$2:G$269, A20) | C20: =COUNTIFS('Cleaned Transactions'!G$2:G$269, A20, 'Cleaned Transactions'!L$2:L$269, "Successful") | D20: =COUNTIFS('Cleaned Transactions'!G$2:G$269, A20, 'Cleaned Transactions'!L$2:L$269, "Failed") | E20: =IFERROR(C20/B20, 0)
A21: UBA | B21: =COUNTIF('Cleaned Transactions'!G$2:G$269, A21) | C21: =COUNTIFS('Cleaned Transactions'!G$2:G$269, A21, 'Cleaned Transactions'!L$2:L$269, "Successful") | D21: =COUNTIFS('Cleaned Transactions'!G$2:G$269, A21, 'Cleaned Transactions'!L$2:L$269, "Failed") | E21: =IFERROR(C21/B21, 0)
A24: 3. Hourly Transaction Distribution & Peak Float Demand
A25: Hour of Day | B25: Tx Count | C25: Total Volume (NGN) | D25: Net Profit (NGN)
A26: 06:00 | B26: =COUNTIF('Cleaned Transactions'!E$2:E$269, 6) | C26: =SUMIFS('Cleaned Transactions'!H$2:H$269, 'Cleaned Transactions'!E$2:E$269, 6, 'Cleaned Transactions'!L$2:L$269, "Successful") | D26: =SUMIF('Cleaned Transactions'!E$2:E$269, 6, 'Cleaned Transactions'!K$2:K$269)
A27: 07:00 | B27: =COUNTIF('Cleaned Transactions'!E$2:E$269, 7) | C27: =SUMIFS('Cleaned Transactions'!H$2:H$269, 'Cleaned Transactions'!E$2:E$269, 7, 'Cleaned Transactions'!L$2:L$269, "Successful") | D27: =SUMIF('Cleaned Transactions'!E$2:E$269, 7, 'Cleaned Transactions'!K$2:K$269)
A28: 08:00 | B28: =COUNTIF('Cleaned Transactions'!E$2:E$269, 8) | C28: =SUMIFS('Cleaned Transactions'!H$2:H$269, 'Cleaned Transactions'!E$2:E$269, 8, 'Cleaned Transactions'!L$2:L$269, "Successful") | D28: =SUMIF('Cleaned Transactions'!E$2:E$269, 8, 'Cleaned Transactions'!K$2:K$269)
A29: 09:00 | B29: =COUNTIF('Cleaned Transactions'!E$2:E$269, 9) | C29: =SUMIFS('Cleaned Transactions'!H$2:H$269, 'Cleaned Transactions'!E$2:E$269, 9, 'Cleaned Transactions'!L$2:L$269, "Successful") | D29: =SUMIF('Cleaned Transactions'!E$2:E$269, 9, 'Cleaned Transactions'!K$2:K$269)
A30: 10:00 | B30: =COUNTIF('Cleaned Transactions'!E$2:E$269, 10) | C30: =SUMIFS('Cleaned Transactions'!H$2:H$269, 'Cleaned Transactions'!E$2:E$269, 10, 'Cleaned Transactions'!L$2:L$269, "Successful") | D30: =SUMIF('Cleaned Transactions'!E$2:E$269, 10, 'Cleaned Transactions'!K$2:K$269)
A31: 11:00 | B31: =COUNTIF('Cleaned Transactions'!E$2:E$269, 11) | C31: =SUMIFS('Cleaned Transactions'!H$2:H$269, 'Cleaned Transactions'!E$2:E$269, 11, 'Cleaned Transactions'!L$2:L$269, "Successful") | D31: =SUMIF('Cleaned Transactions'!E$2:E$269, 11, 'Cleaned Transactions'!K$2:K$269)
A32: 12:00 | B32: =COUNTIF('Cleaned Transactions'!E$2:E$269, 12) | C32: =SUMIFS('Cleaned Transactions'!H$2:H$269, 'Cleaned Transactions'!E$2:E$269, 12, 'Cleaned Transactions'!L$2:L$269, "Successful") | D32: =SUMIF('Cleaned Transactions'!E$2:E$269, 12, 'Cleaned Transactions'!K$2:K$269)
A33: 13:00 | B33: =COUNTIF('Cleaned Transactions'!E$2:E$269, 13) | C33: =SUMIFS('Cleaned Transactions'!H$2:H$269, 'Cleaned Transactions'!E$2:E$269, 13, 'Cleaned Transactions'!L$2:L$269, "Successful") | D33: =SUMIF('Cleaned Transactions'!E$2:E$269, 13, 'Cleaned Transactions'!K$2:K$269)
A34: 14:00 | B34: =COUNTIF('Cleaned Transactions'!E$2:E$269, 14) | C34: =SUMIFS('Cleaned Transactions'!H$2:H$269, 'Cleaned Transactions'!E$2:E$269, 14, 'Cleaned Transactions'!L$2:L$269, "Successful") | D34: =SUMIF('Cleaned Transactions'!E$2:E$269, 14, 'Cleaned Transactions'!K$2:K$269)
A35: 15:00 | B35: =COUNTIF('Cleaned Transactions'!E$2:E$269, 15) | C35: =SUMIFS('Cleaned Transactions'!H$2:H$269, 'Cleaned Transactions'!E$2:E$269, 15, 'Cleaned Transactions'!L$2:L$269, "Successful") | D35: =SUMIF('Cleaned Transactions'!E$2:E$269, 15, 'Cleaned Transactions'!K$2:K$269)
A36: 16:00 | B36: =COUNTIF('Cleaned Transactions'!E$2:E$269, 16) | C36: =SUMIFS('Cleaned Transactions'!H$2:H$269, 'Cleaned Transactions'!E$2:E$269, 16, 'Cleaned Transactions'!L$2:L$269, "Successful") | D36: =SUMIF('Cleaned Transactions'!E$2:E$269, 16, 'Cleaned Transactions'!K$2:K$269)
A37: 17:00 | B37: =COUNTIF('Cleaned Transactions'!E$2:E$269, 17) | C37: =SUMIFS('Cleaned Transactions'!H$2:H$269, 'Cleaned Transactions'!E$2:E$269, 17, 'Cleaned Transactions'!L$2:L$269, "Successful") | D37: =SUMIF('Cleaned Transactions'!E$2:E$269, 17, 'Cleaned Transactions'!K$2:K$269)
A38: 18:00 | B38: =COUNTIF('Cleaned Transactions'!E$2:E$269, 18) | C38: =SUMIFS('Cleaned Transactions'!H$2:H$269, 'Cleaned Transactions'!E$2:E$269, 18, 'Cleaned Transactions'!L$2:L$269, "Successful") | D38: =SUMIF('Cleaned Transactions'!E$2:E$269, 18, 'Cleaned Transactions'!K$2:K$269)
A39: 19:00 | B39: =COUNTIF('Cleaned Transactions'!E$2:E$269, 19) | C39: =SUMIFS('Cleaned Transactions'!H$2:H$269, 'Cleaned Transactions'!E$2:E$269, 19, 'Cleaned Transactions'!L$2:L$269, "Successful") | D39: =SUMIF('Cleaned Transactions'!E$2:E$269, 19, 'Cleaned Transactions'!K$2:K$269)
A40: 20:00 | B40: =COUNTIF('Cleaned Transactions'!E$2:E$269, 20) | C40: =SUMIFS('Cleaned Transactions'!H$2:H$269, 'Cleaned Transactions'!E$2:E$269, 20, 'Cleaned Transactions'!L$2:L$269, "Successful") | D40: =SUMIF('Cleaned Transactions'!E$2:E$269, 20, 'Cleaned Transactions'!K$2:K$269)
A41: 21:00 | B41: =COUNTIF('Cleaned Transactions'!E$2:E$269, 21) | C41: =SUMIFS('Cleaned Transactions'!H$2:H$269, 'Cleaned Transactions'!E$2:E$269, 21, 'Cleaned Transactions'!L$2:L$269, "Successful") | D41: =SUMIF('Cleaned Transactions'!E$2:E$269, 21, 'Cleaned Transactions'!K$2:K$269)
